{"content":[{"id":"29dfc6d3","settings":{"stretch_section":"section-stretched","padding":{"unit":"px","top":"80","right":"0","bottom":"0","left":"0","isLinked":""},"padding_tablet":{"unit":"px","top":"60","right":"15","bottom":"0","left":"15","isLinked":""},"padding_mobile":{"unit":"px","top":"40","right":"0","bottom":"0","left":"0","isLinked":""}},"elements":[{"id":"7ebb920b","settings":{"_column_size":"100","padding":{"unit":"px","top":"0","right":"0","bottom":"0","left":"0","isLinked":""}},"elements":[{"id":"5dc26ee9","settings":{"padding":{"unit":"px","top":"0","right":"0","bottom":"0","left":"0","isLinked":""}},"elements":[{"id":"235455a1","settings":{"_column_size":"100","padding":{"unit":"px","top":"0","right":"15","bottom":"0","left":"15","isLinked":""}},"elements":[{"id":"2e50cc8f","settings":{"section_title":"OUR SERVICE","section_sub_title":"Welcome to our website","show_content":"true","content":"Car Dealer is the best premium automotive responsive WordPress Theme. We provide everything you need to build an <strong> Amazing dealership website <\/strong>developed especially for car sellers, dealers or auto motor retailers. You can use this template for creating website based on any framework and any language.","typography_typography":"custom","typography_font_size":{"unit":"px","size":"40","sizes":[]},"typography_font_size_tablet":{"unit":"px","size":"35","sizes":[]},"typography_font_size_mobile":{"unit":"px","size":"30","sizes":[]},"typography_line_height":{"unit":"px","size":"50","sizes":[]},"typography_line_height_tablet":{"unit":"px","size":"45","sizes":[]},"typography_line_height_mobile":{"unit":"px","size":"40","sizes":[]}},"elements":[],"isInner":false,"widgetType":"cdhl_section-title","elType":"widget"}],"isInner":"1","elType":"column"}],"isInner":"1","elType":"section"},{"id":"1031f882","settings":{"structure":"40","padding":{"unit":"px","top":"0","right":"0","bottom":"0","left":"0","isLinked":""}},"elements":[{"id":"521eb0b6","settings":{"_column_size":"25","margin":{"unit":"px","top":"0","right":"0","bottom":"50","left":"0","isLinked":""},"padding":{"unit":"px","top":"0","right":"15","bottom":"0","left":"15","isLinked":""},"margin_mobile":{"unit":"px","top":"0","right":"0","bottom":"30","left":"0","isLinked":""}},"elements":[{"id":"53ccfcb3","settings":{"border":"true","title":"ALL BRANDS","description":"Printin lorem Ipsum is simply dummy text of the k a galley of type and","icon":{"value":" glyph-icon flaticon-beetle","library":"flaticon"}},"elements":[],"isInner":false,"widgetType":"cdhl_feature-box","elType":"widget"}],"isInner":"1","elType":"column"},{"id":"4ed64ce","settings":{"_column_size":"25","margin":{"unit":"px","top":"0","right":"0","bottom":"50","left":"0","isLinked":""},"padding":{"unit":"px","top":"0","right":"15","bottom":"0","left":"15","isLinked":""},"margin_mobile":{"unit":"px","top":"0","right":"0","bottom":"30","left":"0","isLinked":""}},"elements":[{"id":"26eba1ed","settings":{"border":"true","title":"FREE SUPPORT","description":"Aliquid illo similique minima magni quidem sequi corporis fugiat type and","icon":{"value":" glyph-icon flaticon-interface-1","library":"flaticon"}},"elements":[],"isInner":false,"widgetType":"cdhl_feature-box","elType":"widget"}],"isInner":"1","elType":"column"},{"id":"6eca6812","settings":{"_column_size":"25","margin":{"unit":"px","top":"0","right":"0","bottom":"50","left":"0","isLinked":""},"padding":{"unit":"px","top":"0","right":"15","bottom":"0","left":"15","isLinked":""},"margin_mobile":{"unit":"px","top":"0","right":"0","bottom":"30","left":"0","isLinked":""}},"elements":[{"id":"24b6e338","settings":{"border":"true","title":"DEALERSHIP","description":"Similique minima magni quidem aliquid illo sequi corporis fugiat type and","icon":{"value":" glyph-icon flaticon-key","library":"flaticon"}},"elements":[],"isInner":false,"widgetType":"cdhl_feature-box","elType":"widget"}],"isInner":"1","elType":"column"},{"id":"57d54ee0","settings":{"_column_size":"25","margin":{"unit":"px","top":"0","right":"0","bottom":"50","left":"0","isLinked":""},"padding":{"unit":"px","top":"0","right":"15","bottom":"0","left":"15","isLinked":""},"margin_mobile":{"unit":"px","top":"0","right":"0","bottom":"30","left":"0","isLinked":""}},"elements":[{"id":"41ccb647","settings":{"border":"true","title":"AFFORDABLE","description":"Magni quidem aliquid illo sequi similique minima corporis fugiat type","icon":{"value":" glyph-icon flaticon-wallet","library":"flaticon"}},"elements":[],"isInner":false,"widgetType":"cdhl_feature-box","elType":"widget"}],"isInner":"1","elType":"column"}],"isInner":"1","elType":"section"},{"id":"6461e9ca","settings":{"structure":"40","padding":{"unit":"px","top":"0","right":"0","bottom":"0","left":"0","isLinked":""}},"elements":[{"id":"69329c62","settings":{"_column_size":"25","margin":{"unit":"px","top":"0","right":"0","bottom":"50","left":"0","isLinked":""},"padding":{"unit":"px","top":"0","right":"15","bottom":"0","left":"15","isLinked":""},"margin_mobile":{"unit":"px","top":"0","right":"0","bottom":"30","left":"0","isLinked":""}},"elements":[{"id":"66d3eb57","settings":{"border":"true","title":"OIL CHANGES","description":"The printin lorem Ipsum is simply dummy text of k a galley of type and","icon":{"value":" glyph-icon flaticon-gas-station","library":"flaticon"}},"elements":[],"isInner":false,"widgetType":"cdhl_feature-box","elType":"widget"}],"isInner":"1","elType":"column"},{"id":"6fc16efd","settings":{"_column_size":"25","margin":{"unit":"px","top":"0","right":"0","bottom":"50","left":"0","isLinked":""},"padding":{"unit":"px","top":"0","right":"15","bottom":"0","left":"15","isLinked":""},"margin_mobile":{"unit":"px","top":"0","right":"0","bottom":"30","left":"0","isLinked":""}},"elements":[{"id":"36a31c16","settings":{"border":"true","title":"AIR CONDITIONING","description":"Galley of type lorem Ipsum is simply dummy text of the printin k a type","icon":{"value":" glyph-icon flaticon-air-conditioning","library":"flaticon"}},"elements":[],"isInner":false,"widgetType":"cdhl_feature-box","elType":"widget"}],"isInner":"1","elType":"column"},{"id":"45be09c0","settings":{"_column_size":"25","margin":{"unit":"px","top":"0","right":"0","bottom":"50","left":"0","isLinked":""},"padding":{"unit":"px","top":"0","right":"15","bottom":"0","left":"15","isLinked":""},"margin_mobile":{"unit":"px","top":"0","right":"0","bottom":"30","left":"0","isLinked":""}},"elements":[{"id":"157a0924","settings":{"border":"true","title":"AUTO ELECTRIC","description":"Simply dummy lorem Ipsum is text of the printin k a galley of type and","icon":{"value":" glyph-icon flaticon-electrical-service","library":"flaticon"}},"elements":[],"isInner":false,"widgetType":"cdhl_feature-box","elType":"widget"}],"isInner":"1","elType":"column"},{"id":"25a3662e","settings":{"_column_size":"25","margin":{"unit":"px","top":"0","right":"0","bottom":"50","left":"0","isLinked":""},"padding":{"unit":"px","top":"0","right":"15","bottom":"0","left":"15","isLinked":""},"margin_mobile":{"unit":"px","top":"0","right":"0","bottom":"40","left":"0","isLinked":""}},"elements":[{"id":"6cc57ce1","settings":{"border":"true","title":"TRANSMISSION","description":"Dolorem voluptates is simply dummy text of the printin k a galley of type","icon":{"value":" glyph-icon flaticon-gearstick","library":"flaticon"}},"elements":[],"isInner":false,"widgetType":"cdhl_feature-box","elType":"widget"}],"isInner":"1","elType":"column"}],"isInner":"1","elType":"section"}],"isInner":"","elType":"column"}],"isInner":"","elType":"section"},{"id":"53c76145","settings":{"layout":"full_width","stretch_section":"section-stretched","structure":"30","background_background":"classic","background_position":"center center","background_repeat":"no-repeat","background_size":"cover","padding":{"unit":"px","top":"0","right":"0","bottom":"0","left":"0","isLinked":""}},"elements":[{"id":"56fa0d3c","settings":{"_column_size":"33","background_background":"classic","background_position":"bottom left","background_repeat":"no-repeat","background_size":"contain","background_hover_background":"classic","background_hover_transition":{"unit":"px","size":"0.5","sizes":[]},"padding":{"unit":"px","top":"0","right":"0","bottom":"0","left":"0","isLinked":""},"_inline_size_tablet":"100","hide_tablet":"hidden-tablet","hide_mobile":"hidden-phone","background_image":{"url":"http:\/\/sample-data.potenzaglobal.com\/cardealer\/elementor-demo\/placeholder_428x355-left.jpg","id":"22374"},"css_classes":"object-left-bottom"},"elements":[],"isInner":"","elType":"column"},{"id":"72a04a07","settings":{"_column_size":"33","padding":{"unit":"px","top":"90","right":"15","bottom":"90","left":"15","isLinked":""},"padding_tablet":{"unit":"px","top":"20","right":"15","bottom":"20","left":"15","isLinked":""},"padding_mobile":{"unit":"px","top":"20","right":"15","bottom":"40","left":"15","isLinked":""},"_inline_size_tablet":"100"},"elements":[{"id":"540ca436","settings":{"image":{"url":"http:\/\/sample-data.potenzaglobal.com\/cardealer\/elementor-demo\/placeholder_430x450.jpg","id":"16375"},"image_size":"custom","image_custom_dimension":{"width":"80","height":"80"},"align":"center","image_border_radius":{"unit":"px","top":"50","right":"50","bottom":"50","left":"50","isLinked":"1"},"_margin":{"unit":"px","top":"0","right":"0","bottom":"5","left":"0","isLinked":""}},"elements":[],"isInner":false,"widgetType":"image","elType":"widget"},{"id":"6aa1a7b2","settings":{"editor":"<p>Have any question ?<\/p>","align":"center","_margin":{"unit":"px","top":"0","right":"0","bottom":"10","left":"0","isLinked":""}},"elements":[],"isInner":false,"widgetType":"text-editor","elType":"widget"},{"id":"6f35352c","settings":{"title":"(007) 123 456 7890","align":"center","title_color":"#DB2D2E","typography_typography":"custom","typography_font_size_tablet":{"unit":"px","size":"35","sizes":[]},"typography_font_size_mobile":{"unit":"px","size":"30","sizes":[]},"typography_font_weight":"500","typography_line_height_tablet":{"unit":"px","size":"45","sizes":[]},"typography_line_height_mobile":{"unit":"px","size":"40","sizes":[]}},"elements":[],"isInner":false,"widgetType":"heading","elType":"widget"}],"isInner":"","elType":"column"},{"id":"25b0edbd","settings":{"_column_size":"33","padding":{"unit":"px","top":"0","right":"0","bottom":"0","left":"0","isLinked":""},"_inline_size_tablet":"100","hide_tablet":"hidden-tablet","hide_mobile":"hidden-phone","background_background":"classic","background_image":{"url":"http:\/\/sample-data.potenzaglobal.com\/cardealer\/elementor-demo\/placeholder_428x355-right.jpg","id":"22373"},"background_position":"bottom right","background_repeat":"no-repeat","background_size":"contain","css_classes":"object-right-bottom"},"elements":[],"isInner":"","elType":"column"}],"isInner":"","elType":"section"}],"page_settings":{"template":"elementor_header_footer"},"version":"0.4","title":"Elementor Library","type":"wp-page"}